{
    "/js/gravity.js": "/js/gravity.js?id=20ff05de987acd9e9a15",
    "/css/gravity.css": "/css/gravity.css?id=5254d90092a9b1a1e2c1",
    "/img/audio-large.svg": "/img/audio-large.svg?id=fca6a67c7ef06d00ef4a",
    "/img/audio-small.svg": "/img/audio-small.svg?id=48f5a5c5ff1cfd2cb375",
    "/img/document-large.svg": "/img/document-large.svg?id=5c7cacec26ee17c609d5",
    "/img/document-small.svg": "/img/document-small.svg?id=814d189ff718fee22753",
    "/img/folder.svg": "/img/folder.svg?id=30ada991dcf230bae934",
    "/img/icons.sketch": "/img/icons.sketch?id=ade850fc2fca6e483f76",
    "/img/image-large.svg": "/img/image-large.svg?id=c1f888ae5b9aa3205da2",
    "/img/image-small.svg": "/img/image-small.svg?id=ce4607b6b20343819a0e",
    "/img/logo-light.svg": "/img/logo-light.svg?id=c405004e06df8ab3925e",
    "/img/logo.svg": "/img/logo.svg?id=64c15de58b4f4505abad",
    "/img/misc-large.svg": "/img/misc-large.svg?id=efc91b343d8a0a292cb9",
    "/img/misc-small.svg": "/img/misc-small.svg?id=7a776470be10de0be46a",
    "/img/video-large.svg": "/img/video-large.svg?id=c7e14f102962217024ed",
    "/img/video-small.svg": "/img/video-small.svg?id=23d303a164b4e0b276a6"
}
